MANIFEST.in
README.md
extract_h264.py
pynvr.py
pynvr_config.py
rtsp.py
setup.cfg
setup.py
pylive555/module.cpp
pynvr.egg-info/PKG-INFO
pynvr.egg-info/SOURCES.txt
pynvr.egg-info/dependency_links.txt
pynvr.egg-info/requires.txt
pynvr.egg-info/top_level.txt
shared/__init__.py
shared/camera.py
shared/common.py
shared/daemon.py
shared/nvrconfig.py
shared/reap.py
static/__init__.py
static/camera.html
static/downloads.html
static/index.html
static/jquery-2.2.0.min.js
static/jquery.hoverIntent.minified.js
static/jquery.lazyload.min.js
static/jquery.unveil.js
static/jquery.waypoints.min.js
static/left.png
static/loading.gif
static/moment.min.js
static/right.png
static/web.html
static/__pycache__/__init__.cpython-34.pyc
static/jquery-ui-1.11.4/index.html
static/jquery-ui-1.11.4/jquery-ui.css
static/jquery-ui-1.11.4/jquery-ui.js
static/jquery-ui-1.11.4/jquery-ui.min.css
static/jquery-ui-1.11.4/jquery-ui.min.js
static/jquery-ui-1.11.4/jquery-ui.structure.css
static/jquery-ui-1.11.4/jquery-ui.structure.min.css
static/jquery-ui-1.11.4/jquery-ui.theme.css
static/jquery-ui-1.11.4/jquery-ui.theme.min.css
static/jquery-ui-1.11.4/images/ui-bg_diagonals-thick_18_b81900_40x40.png
static/jquery-ui-1.11.4/images/ui-bg_diagonals-thick_20_666666_40x40.png
static/jquery-ui-1.11.4/images/ui-bg_flat_10_000000_40x100.png
static/jquery-ui-1.11.4/images/ui-bg_glass_100_f6f6f6_1x400.png
static/jquery-ui-1.11.4/images/ui-bg_glass_100_fdf5ce_1x400.png
static/jquery-ui-1.11.4/images/ui-bg_glass_65_ffffff_1x400.png
static/jquery-ui-1.11.4/images/ui-bg_gloss-wave_35_f6a828_500x100.png
static/jquery-ui-1.11.4/images/ui-bg_highlight-soft_100_eeeeee_1x100.png
static/jquery-ui-1.11.4/images/ui-bg_highlight-soft_75_ffe45c_1x100.png
static/jquery-ui-1.11.4/images/ui-icons_222222_256x240.png
static/jquery-ui-1.11.4/images/ui-icons_228ef1_256x240.png
static/jquery-ui-1.11.4/images/ui-icons_ef8c08_256x240.png
static/jquery-ui-1.11.4/images/ui-icons_ffd27a_256x240.png
static/jquery-ui-1.11.4/images/ui-icons_ffffff_256x240.png