Metadata-Version: 1.0
Name: pynvr
Version: 0.1.12
Summary: Network Video Recorder for recording h264 rtsp IP cameras
Home-page: https://gitlab.com/hoyle.hoyle/pynvr
Author: Jack Strohm
Author-email: hoyle.hoyle@gmail.com
License: MIT
Keywords: nvr,security,recording,ip camera,rtsp,h264,camera
Platform: UNKNOWN
